tg_migrator/__init__.py
tg_migrator/config.py
tg_migrator/main.py
tg_migrator/versions/20240703224042_creating_Person_vertex.py
tg_migrator/versions/20240703224217_creating_freind_edge.py
tg_migrator/versions/20240703224218_creating_location.py
tg_migrator/versions/20240703224219_creating_located.py
tg_migrator/versions/20240707080142_liked_vertex.py
tg_migrator/versions/20240707080757_liked_edge_between_Person_and_Post.py
tg_migrator/versions/20240809201406_Hashtag_vertex_and_Edge.py
tg_migrator/versions/20240810001920_adding_new_vertex.py
tg_migrator/versions/20240810204221_creating_socail_graph.py
tg_migrator/versions/20240810205611_add_location.py
tg_migrator/versions/__init__.py
tg_migrator-0.2.0.dist-info/METADATA
tg_migrator-0.2.0.dist-info/WHEEL
tg_migrator-0.2.0.dist-info/entry_points.txt
tg_migrator-0.2.0.dist-info/top_level.txt
tg_migrator-0.2.0.dist-info/RECORD
