Metadata-Version: 2.1
Name: tg-migrator
Version: 0.2.0
Summary: migration tool for tigergraph
Author: Mohammad Ashraf
Requires-Dist: configparser
Requires-Dist: pyTigerGraph
Requires-Dist: tqdm
